azure/cognitiveservices/vision/face/__init__.py
azure/cognitiveservices/vision/face/_configuration.py
azure/cognitiveservices/vision/face/_face_client.py
azure/cognitiveservices/vision/face/py.typed
azure/cognitiveservices/vision/face/version.py
azure/cognitiveservices/vision/face/models/__init__.py
azure/cognitiveservices/vision/face/models/_face_client_enums.py
azure/cognitiveservices/vision/face/models/_models.py
azure/cognitiveservices/vision/face/models/_models_py3.py
azure/cognitiveservices/vision/face/operations/__init__.py
azure/cognitiveservices/vision/face/operations/_face_list_operations.py
azure/cognitiveservices/vision/face/operations/_face_operations.py
azure/cognitiveservices/vision/face/operations/_large_face_list_operations.py
azure/cognitiveservices/vision/face/operations/_large_person_group_operations.py
azure/cognitiveservices/vision/face/operations/_large_person_group_person_operations.py
azure/cognitiveservices/vision/face/operations/_person_group_operations.py
azure/cognitiveservices/vision/face/operations/_person_group_person_operations.py
azure/cognitiveservices/vision/face/operations/_snapshot_operations.py
azure_cognitiveservices_vision_face-0.6.1.dist-info/LICENSE
azure_cognitiveservices_vision_face-0.6.1.dist-info/METADATA
azure_cognitiveservices_vision_face-0.6.1.dist-info/WHEEL
azure_cognitiveservices_vision_face-0.6.1.dist-info/top_level.txt
azure_cognitiveservices_vision_face-0.6.1.dist-info/RECORD
